evolocity/__init__.py
evolocity/datasets.py
evolocity/logging.py
evolocity/pl.py
evolocity/pp.py
evolocity/settings.py
evolocity/tl.py
evolocity/plotting/__init__.py
evolocity/plotting/docs.py
evolocity/plotting/evolocity_plotting.py
evolocity/plotting/palettes.py
evolocity/plotting/scatter.py
evolocity/plotting/utils.py
evolocity/plotting/velocity_contour.py
evolocity/plotting/velocity_embedding.py
evolocity/plotting/velocity_embedding_grid.py
evolocity/plotting/velocity_embedding_stream.py
evolocity/preprocessing/__init__.py
evolocity/preprocessing/featurize_seqs.py
evolocity/preprocessing/neighbors.py
evolocity/preprocessing/utils.py
evolocity/tools/__init__.py
evolocity/tools/fb_model.py
evolocity/tools/fb_semantics.py
evolocity/tools/random_walk.py
evolocity/tools/tape_model.py
evolocity/tools/tape_semantics.py
evolocity/tools/terminal_states.py
evolocity/tools/transition_matrix.py
evolocity/tools/utils.py
evolocity/tools/velocity_embedding.py
evolocity/tools/velocity_graph.py
evolocity/tools/velocity_model.py
evolocity/tools/velocity_onehot.py
evolocity/tools/velocity_pseudotime.py
evolocity-1.1.dist-info/licenses/LICENSE
evolocity-1.1.dist-info/METADATA
evolocity-1.1.dist-info/WHEEL
evolocity-1.1.dist-info/top_level.txt
evolocity-1.1.dist-info/RECORD
