Metadata-Version: 2.4
Name: evolocity
Version: 1.1
Summary: Evolutionary velocity with protein language models
Home-page: https://github.com/brianhie/evolocity
Download-URL: https://github.com/brianhie/evolocity
Author: Brian Hie
Author-email: brianhie@stanford.edu
License: MIT
Keywords: evolution,velocity,evolocity,protein,language model
Requires-Python: >=3.6
License-File: LICENSE
Requires-Dist: biopython>=1.80
Requires-Dist: louvain>=0.6.1
Requires-Dist: matplotlib>=3.1.1
Requires-Dist: numpy>=1.17.2
Requires-Dist: pandas>=0.25.1
Requires-Dist: python-igraph>=0.8.3
Requires-Dist: scanpy>=1.4.5.1
Requires-Dist: scikit-learn>=0.21.3
Requires-Dist: scipy>=1.3.1
Requires-Dist: seaborn>=0.9.0
Requires-Dist: torch>=1.7.1
Dynamic: author
Dynamic: author-email
Dynamic: description
Dynamic: download-url
Dynamic: home-page
Dynamic: keywords
Dynamic: license
Dynamic: license-file
Dynamic: requires-dist
Dynamic: requires-python
Dynamic: summary
